<?xml version="1.0" encoding="utf-8"?>
<TextureAtlas imagePath="logoBumpin.png">
	<!-- Created with Adobe Animate version 21.0.0.35450 -->
	<!-- http://www.adobe.com/products/animate.html -->
	<SubTexture name="logo bumpin0000" x="0" y="0" width="840" height="630"/>
	<SubTexture name="logo bumpin0001" x="0" y="0" width="840" height="630"/>
	<SubTexture name="logo bumpin0002" x="840" y="0" width="840" height="630"/>
	<SubTexture name="logo bumpin0003" x="840" y="0" width="840" height="630"/>
	<SubTexture name="logo bumpin0004" x="0" y="630" width="840" height="630"/>
	<SubTexture name="logo bumpin0005" x="0" y="630" width="840" height="630"/>
	<SubTexture name="logo bumpin0006" x="840" y="630" width="840" height="630"/>
	<SubTexture name="logo bumpin0007" x="840" y="630" width="840" height="630"/>
	<SubTexture name="logo bumpin0008" x="840" y="630" width="840" height="630"/>
</TextureAtlas>
